src/mcp_email_client/__init__.py
src/mcp_email_client/__main__.py
src/mcp_email_client/config.py
src/mcp_email_client/mailhandler.py
src/mcp_email_client/server.py
src/mcp_email_client/config/.gitignore
template/.gitignore
orange_mcp_email_client-0.1.0.dist-info/METADATA
orange_mcp_email_client-0.1.0.dist-info/WHEEL
orange_mcp_email_client-0.1.0.dist-info/entry_points.txt
orange_mcp_email_client-0.1.0.dist-info/RECORD
