Metadata-Version: 2.4
Name: orange-mcp-email-client
Version: 0.1.0
Summary: Add your description here
Requires-Python: >=3.12
Requires-Dist: asyncio>=3.4.3
Requires-Dist: imapclient>=3.0.1
Requires-Dist: mcp[cli]>=1.3.0
Requires-Dist: pydantic>=2.10.6
